fabrictestbed_extensions/__init__.py
fabrictestbed_extensions/editors/__init__.py
fabrictestbed_extensions/editors/abc_topology_editor.py
fabrictestbed_extensions/editors/cytoscape_topology_editor.py
fabrictestbed_extensions/editors/geo_topology_editor.py
fabrictestbed_extensions/fablib/__init__.py
fabrictestbed_extensions/fablib/component.py
fabrictestbed_extensions/fablib/fablib.py
fabrictestbed_extensions/fablib/facility_port.py
fabrictestbed_extensions/fablib/interface.py
fabrictestbed_extensions/fablib/network_service.py
fabrictestbed_extensions/fablib/node.py
fabrictestbed_extensions/fablib/resources.py
fabrictestbed_extensions/fablib/slice.py
fabrictestbed_extensions/images/__init__.py
fabrictestbed_extensions/images/fabric_logo.png
fabrictestbed_extensions/images/server.png
fabrictestbed_extensions/images/slice_rack.png
fabrictestbed_extensions/utils/__init__.py
fabrictestbed_extensions/utils/abc_utils.py
fabrictestbed_extensions/utils/node.py
fabrictestbed_extensions/utils/slice.py
fabrictestbed_fablib/__init__.py
fabrictestbed_fablib/abc_fablib.py
fabrictestbed_fablib/component.py
fabrictestbed_fablib/fablib.py
fabrictestbed_fablib/facility_port.py
fabrictestbed_fablib/interface.py
fabrictestbed_fablib/network_service.py
fabrictestbed_fablib/node.py
fabrictestbed_fablib/resources.py
fabrictestbed_fablib/slice.py
fabrictestbed_fablib-1.4.6rc1.dist-info/LICENSE
fabrictestbed_fablib-1.4.6rc1.dist-info/METADATA
fabrictestbed_fablib-1.4.6rc1.dist-info/WHEEL
fabrictestbed_fablib-1.4.6rc1.dist-info/top_level.txt
fabrictestbed_fablib-1.4.6rc1.dist-info/RECORD
