Metadata-Version: 2.1
Name: fabrictestbed-fablib
Version: 1.4.6rc1
Summary: FABRIC Python Client Library and CLI Extensions
Author-email: Paul Ruth <pruth@renci.org>, Komal Thareja <kthare10@renci.org>
License: MIT License
Project-URL: Homepage, https://fabric-testbed.net/
Project-URL: Sources, https://github.com/fabric-testbed/fabrictestbed-extensions
Project-URL: Documentation, https://fabric-fablib.readthedocs.io/
Project-URL: ChangeLog, https://github.com/fabric-testbed/fabrictestbed-extensions/blob/main/CHANGELOG.md
Classifier: Programming Language :: Python :: 3
Classifier: License :: OSI Approved :: MIT License
Classifier: Operating System :: OS Independent
Requires-Python: >=3.9
License-File: LICENSE
Requires-Dist: ipycytoscape
Requires-Dist: ipywidgets
Requires-Dist: ipyleaflet
Requires-Dist: tabulate
Requires-Dist: fabrictestbed (==1.4.4)
Requires-Dist: paramiko
Requires-Dist: jinja2 (>=3.0.0)
Requires-Dist: pandas
Requires-Dist: numpy
Requires-Dist: ipython (==8.12.0)
Provides-Extra: doc
Requires-Dist: sphinx ; extra == 'doc'
Requires-Dist: furo ; extra == 'doc'
Provides-Extra: test
Requires-Dist: pytest ; extra == 'test'
Requires-Dist: coverage[toml] ; extra == 'test'
